StreamAudio/__init__.py
StreamAudio/stream_audio.py
StreamAudio-0.2.1.dist-info/METADATA
StreamAudio-0.2.1.dist-info/WHEEL
StreamAudio-0.2.1.dist-info/top_level.txt
StreamAudio-0.2.1.dist-info/RECORD
