Metadata-Version: 2.1
Name: StreamAudio
Version: 0.2.1
Summary: A Python package for real-time audio streaming in memory for flexible use cases
Home-page: https://github.com/PierreGode/streamaudio
Author: Pierre Gode
Author-email: pierre@gode.one
Classifier: Programming Language :: Python :: 3
Classifier: License :: OSI Approved :: MIT License
Classifier: Operating System :: OS Independent
Requires-Python: >=3.7
Requires-Dist: pyaudio
